setup.py
bin/treeoflife-server
treeoflife/__init__.py
treeoflife/alarms.py
treeoflife/conftest.py
treeoflife/editor_launch.py
treeoflife/exceptions.py
treeoflife/file_storage.py
treeoflife/interact_searching.py
treeoflife/main.py
treeoflife/navigation.py
treeoflife/ordereddict.py
treeoflife/parseutil.py
treeoflife/searching.py
treeoflife/timefmt.py
treeoflife/tracker.py
treeoflife/userinterface.py
treeoflife/util.py
treeoflife.egg-info/PKG-INFO
treeoflife.egg-info/SOURCES.txt
treeoflife.egg-info/dependency_links.txt
treeoflife.egg-info/requires.txt
treeoflife.egg-info/top_level.txt
treeoflife/nodes/__init__.py
treeoflife/nodes/days.py
treeoflife/nodes/import_all.py
treeoflife/nodes/misc.py
treeoflife/nodes/node.py
treeoflife/nodes/recordkeeping.py
treeoflife/nodes/references.py
treeoflife/nodes/tasks.py
treeoflife/nodes/testnodes.py
treeoflife/nodes/test/__init__.py
treeoflife/nodes/test/test_days.py
treeoflife/nodes/test/test_misc.py
treeoflife/nodes/test/test_node.py
treeoflife/nodes/test/test_recordkeeping.py
treeoflife/nodes/test/test_references.py
treeoflife/test/__init__.py
treeoflife/test/test_alarm.py
treeoflife/test/test_exceptions.py
treeoflife/test/test_file_storage.py
treeoflife/test/test_main.py
treeoflife/test/test_navigation.py
treeoflife/test/test_nodes.py
treeoflife/test/test_parseutil.py
treeoflife/test/test_pep8.py
treeoflife/test/test_searching.py
treeoflife/test/test_time.py
treeoflife/test/test_tracker.py
treeoflife/test/test_userinterface.py
treeoflife/test/util.py