Metadata-Version: 1.0
Name: treeoflife
Version: 0.0.4
Summary: A Tree of your Life (end-user application)
Home-page: https://github.com/lahwran/tree-of-life
Author: lahwran
Author-email: lahwran0@gmail.com
License: MIT
Download-URL: https://github.com/lahwran/tree-of-life/tarball/0.0.4
Platform: UNKNOWN
Classifier: Development Status :: 3 - Alpha
Classifier: Environment :: Web Environment
Classifier: Environment :: MacOS X
Classifier: Framework :: Twisted
Classifier: Intended Audience :: End Users/Desktop
Classifier: License :: OSI Approved :: MIT License
Classifier: Natural Language :: English
Classifier: Operating System :: MacOS :: MacOS X
Classifier: Operating System :: OS Independent
Classifier: Programming Language :: Python :: 2.7
Classifier: Programming Language :: Python :: 2 :: Only
Classifier: Programming Language :: Python :: Implementation :: PyPy
Classifier: Programming Language :: Python :: Implementation :: CPython
Classifier: Programming Language :: Objective C
Classifier: Programming Language :: JavaScript
Classifier: Topic :: Office/Business :: Scheduling
Classifier: Topic :: Software Development :: Bug Tracking
